{
    "nordic-wallpaper": {
        "cargoLocks": null,
        "date": "2025-02-10",
        "extract": null,
        "name": "nordic-wallpaper",
        "passthru": null,
        "pinned": false,
        "src": {
            "deepClone": false,
            "fetchSubmodules": false,
            "leaveDotGit": false,
            "name": null,
            "owner": "linuxdotexe",
            "repo": "nordic-wallpapers",
            "rev": "1b0102fb3fc39d29bf9d1c5385b1c1ad873c7e54",
            "sha256": "sha256-KDkTnEBdL/DQ7ZJ62t3vTAO3OwE69KDsQ5gSTWh84GM=",
            "sparseCheckout": [],
            "type": "github"
        },
        "version": "1b0102fb3fc39d29bf9d1c5385b1c1ad873c7e54"
    },
    "pop-wallpaper": {
        "cargoLocks": null,
        "date": null,
        "extract": null,
        "name": "pop-wallpaper",
        "passthru": null,
        "pinned": false,
        "src": {
            "deepClone": false,
            "fetchSubmodules": false,
            "leaveDotGit": false,
            "name": null,
            "owner": "George-Miao",
            "repo": "wallpaper",
            "rev": "f79c2e",
            "sha256": "sha256-3VYnGGE/N8GWGWTCHYFQxMva1Ye8NIaByfzBCCyPUPU=",
            "sparseCheckout": [],
            "type": "github"
        },
        "version": "f79c2e"
    },
    "vscode-darwin-insider": {
        "cargoLocks": null,
        "date": null,
        "extract": null,
        "name": "vscode-darwin-insider",
        "passthru": null,
        "pinned": false,
        "src": {
            "sha256": "sha256-U88R6R53Sg+mzPLd2Ny/ZTeVsXDzbGE8psb6Tdwi+IY=",
            "type": "tarball",
            "url": "https://vscode.download.prss.microsoft.com/dbazure/download/insider/1217722c34017d9bd87e804e80efabba5a1e3226/VSCode-darwin-universal.zip"
        },
        "version": "https://vscode.download.prss.microsoft.com/dbazure/download/insider/1217722c34017d9bd87e804e80efabba5a1e3226/VSCode-darwin-universal.zip"
    },
    "vscode-darwin-stable": {
        "cargoLocks": null,
        "date": null,
        "extract": null,
        "name": "vscode-darwin-stable",
        "passthru": null,
        "pinned": false,
        "src": {
            "sha256": "sha256-yP0C8dUPE+d742qdEOHhoeRcNqDX2M5u0Cot+37c1d4=",
            "type": "tarball",
            "url": "https://vscode.download.prss.microsoft.com/dbazure/download/stable/0f0d87fa9e96c856c5212fc86db137ac0d783365/VSCode-darwin-universal.zip"
        },
        "version": "https://vscode.download.prss.microsoft.com/dbazure/download/stable/0f0d87fa9e96c856c5212fc86db137ac0d783365/VSCode-darwin-universal.zip"
    },
    "vscode-linux-insider": {
        "cargoLocks": null,
        "date": null,
        "extract": null,
        "name": "vscode-linux-insider",
        "passthru": null,
        "pinned": false,
        "src": {
            "sha256": "sha256-vLjbVm459SobQfeR9PqfcGxEhw9SWxBdB+/kTOJcyNM=",
            "type": "tarball",
            "url": "https://vscode.download.prss.microsoft.com/dbazure/download/insider/1217722c34017d9bd87e804e80efabba5a1e3226/code-insider-x64-1758518510.tar.gz"
        },
        "version": "https://vscode.download.prss.microsoft.com/dbazure/download/insider/1217722c34017d9bd87e804e80efabba5a1e3226/code-insider-x64-1758518510.tar.gz"
    },
    "vscode-linux-stable": {
        "cargoLocks": null,
        "date": null,
        "extract": null,
        "name": "vscode-linux-stable",
        "passthru": null,
        "pinned": false,
        "src": {
            "sha256": "sha256-yDPZvryeEOmu0nDiSenq8joo5SOEAJw/9G2IscNsNYE=",
            "type": "tarball",
            "url": "https://vscode.download.prss.microsoft.com/dbazure/download/stable/0f0d87fa9e96c856c5212fc86db137ac0d783365/code-stable-x64-1758154038.tar.gz"
        },
        "version": "https://vscode.download.prss.microsoft.com/dbazure/download/stable/0f0d87fa9e96c856c5212fc86db137ac0d783365/code-stable-x64-1758154038.tar.gz"
    }
}